bomiot_core-0.5.8.dist-info/METADATA
bomiot_core-0.5.8.dist-info/WHEEL
bomiot_core-0.5.8.dist-info/licenses/LICENSE
bomiot_core/__init__.py
bomiot_core/bomiot_core.cpython-312-x86_64-linux-gnu.so
bomiot_core-0.5.8.dist-info/RECORD
